mnapy/ACCurrent.py
mnapy/ACCurrentLimits.py
mnapy/ACSource.py
mnapy/ACSourceLimits.py
mnapy/ADCModule.py
mnapy/ADCModuleLimits.py
mnapy/ANDGate.py
mnapy/ANDGateLimits.py
mnapy/AbsoluteValue.py
mnapy/AbsoluteValueLimits.py
mnapy/Adder.py
mnapy/AdderLimits.py
mnapy/AmMeter.py
mnapy/AmMeterLimits.py
mnapy/Bridge.py
mnapy/BridgeLimits.py
mnapy/Capacitor.py
mnapy/CapacitorLimits.py
mnapy/Constant.py
mnapy/ConstantLimits.py
mnapy/Constants.py
mnapy/CurrentControlledCurrentSource.py
mnapy/CurrentControlledCurrentSourceLimits.py
mnapy/CurrentControlledVoltageSource.py
mnapy/CurrentControlledVoltageSourceLimits.py
mnapy/DACModule.py
mnapy/DACModuleLimits.py
mnapy/DCCurrent.py
mnapy/DCCurrentLimits.py
mnapy/DCSource.py
mnapy/DCSourceLimits.py
mnapy/DFlipFlop.py
mnapy/DFlipFlopLimits.py
mnapy/DifferentiatorModule.py
mnapy/DifferentiatorModuleLimits.py
mnapy/Diode.py
mnapy/DiodeLimits.py
mnapy/Divider.py
mnapy/DividerLimits.py
mnapy/Element.py
mnapy/Engine.py
mnapy/Flags.py
mnapy/Fuse.py
mnapy/FuseLimits.py
mnapy/GainBlock.py
mnapy/GainBlockLimits.py
mnapy/Global.py
mnapy/GreaterThan.py
mnapy/GreaterThanLimits.py
mnapy/Ground.py
mnapy/GroundLimits.py
mnapy/HighPassFilter.py
mnapy/HighPassFilterLimits.py
mnapy/Inductor.py
mnapy/InductorLimits.py
mnapy/IntegratorModule.py
mnapy/IntegratorModuleLimits.py
mnapy/KeyPair.py
mnapy/LightEmittingDiode.py
mnapy/LightEmittingDiodeLimits.py
mnapy/Limit.py
mnapy/LookUpTable.py
mnapy/LookUpTableLimits.py
mnapy/LowPassFilter.py
mnapy/LowPassFilterLimits.py
mnapy/Multiplier.py
mnapy/MultiplierLimits.py
mnapy/NANDGate.py
mnapy/NANDGateLimits.py
mnapy/NChannelMOSFET.py
mnapy/NChannelMOSFETLimits.py
mnapy/NORGate.py
mnapy/NORGateLimits.py
mnapy/NOTGate.py
mnapy/NOTGateLimits.py
mnapy/NPNBipolarJunctionTransistor.py
mnapy/NPNBipolarJunctionTransistorLimits.py
mnapy/Net.py
mnapy/NetLimits.py
mnapy/Node.py
mnapy/NodeManager.py
mnapy/NodeNetwork.py
mnapy/NodeReference.py
mnapy/Note.py
mnapy/NoteLimits.py
mnapy/ORGate.py
mnapy/ORGateLimits.py
mnapy-1.2.25.dist-info/LICENSE.txt
mnapy-1.2.25.dist-info/METADATA
mnapy-1.2.25.dist-info/WHEEL
mnapy-1.2.25.dist-info/top_level.txt
mnapy-1.2.25.dist-info/RECORD
