Metadata-Version: 2.1
Name: mnapy
Version: 1.2.25
Summary: Dynamic Cross Platform Circuit Simulation Platform.
Home-page: https://github.com/SummersEdge23/mnapy
Author: Christian Nimako-Boateng
Author-email: summersedge23@gmail.com
License: MIT
Platform: UNKNOWN
